pymodaq_plugins_alcatel/__init__.py
pymodaq_plugins_alcatel/utils.py
pymodaq_plugins_alcatel/daq_move_plugins/__init__.py
pymodaq_plugins_alcatel/daq_viewer_plugins/__init__.py
pymodaq_plugins_alcatel/daq_viewer_plugins/plugins_0D/__init__.py
pymodaq_plugins_alcatel/daq_viewer_plugins/plugins_0D/daq_0Dviewer_ACM1000.py
pymodaq_plugins_alcatel/daq_viewer_plugins/plugins_1D/__init__.py
pymodaq_plugins_alcatel/daq_viewer_plugins/plugins_2D/__init__.py
pymodaq_plugins_alcatel/daq_viewer_plugins/plugins_ND/__init__.py
pymodaq_plugins_alcatel/extensions/__init__.py
pymodaq_plugins_alcatel/hardware/ACM1000_wrapper.py
pymodaq_plugins_alcatel/hardware/__init__.py
pymodaq_plugins_alcatel/models/__init__.py
pymodaq_plugins_alcatel/resources/VERSION
pymodaq_plugins_alcatel/resources/__init__.py
pymodaq_plugins_alcatel/resources/config_template.toml
pymodaq_plugins_alcatel-1.1.0.dist-info/LICENSE
pymodaq_plugins_alcatel-1.1.0.dist-info/METADATA
pymodaq_plugins_alcatel-1.1.0.dist-info/WHEEL
pymodaq_plugins_alcatel-1.1.0.dist-info/entry_points.txt
pymodaq_plugins_alcatel-1.1.0.dist-info/top_level.txt
pymodaq_plugins_alcatel-1.1.0.dist-info/RECORD
