Metadata-Version: 2.1
Name: pymodaq-plugins-alcatel
Version: 1.1.0
Summary: PyMoDAQ plugin for the Alcatel ACM1000 6-port gauge controller.
Home-page: https://github.com/Titouan-Gadeyne/pymodaq_plugins_alcatel
Author: Titouan GADEYNE
Author-email: titouan.gadeyne@cea.fr
License: MIT
Classifier: Programming Language :: Python :: 3
Classifier: Development Status :: 5 - Production/Stable
Classifier: Environment :: Other Environment
Classifier: Intended Audience :: Science/Research
Classifier: Topic :: Scientific/Engineering :: Human Machine Interfaces
Classifier: Topic :: Scientific/Engineering :: Visualization
Classifier: License :: OSI Approved :: MIT License
Classifier: Operating System :: OS Independent
Classifier: Topic :: Software Development :: Libraries :: Python Modules
Classifier: Topic :: Software Development :: User Interfaces
License-File: LICENSE
Requires-Dist: toml
Requires-Dist: pymodaq >=4.0.0
Requires-Dist: pylablib
